Mantissa-0.9.0.dist-info/DESCRIPTION.rst
Mantissa-0.9.0.dist-info/METADATA
Mantissa-0.9.0.dist-info/RECORD
Mantissa-0.9.0.dist-info/WHEEL
Mantissa-0.9.0.dist-info/metadata.json
Mantissa-0.9.0.dist-info/top_level.txt
axiom/plugins/mantissacmd.py
axiom/plugins/offeringcmd.py
axiom/plugins/webcmd.py
nevow/plugins/mantissa_package.py
xmantissa/__init__.py
xmantissa/_recordattr.py
xmantissa/_version.py
xmantissa/_webidgen.py
xmantissa/_webutil.py
xmantissa/ampserver.py
xmantissa/cachejs.py
xmantissa/endpoint.py
xmantissa/error.py
xmantissa/fragmentutils.py
xmantissa/fulltext.py
xmantissa/interstore.py
xmantissa/ixmantissa.py
xmantissa/liveform.py
xmantissa/myaccount.py
xmantissa/offering.py
xmantissa/people.py
xmantissa/port.py
xmantissa/prefs.py
xmantissa/product.py
xmantissa/publicresource.py
xmantissa/publicweb.py
xmantissa/reset.rfc2822
xmantissa/scrolltable.py
xmantissa/search.py
xmantissa/settings.py
xmantissa/sharing.py
xmantissa/signup.py
xmantissa/signup.rfc2822
xmantissa/smtp.py
xmantissa/statcollector.tac
xmantissa/stats.py
xmantissa/suspension.py
xmantissa/tdb.py
xmantissa/tdbview.py
xmantissa/terminal.py
xmantissa/web.py
xmantissa/webadmin.py
xmantissa/webapp.py
xmantissa/webgestalt.py
xmantissa/webnav.py
xmantissa/websession.py
xmantissa/websharing.py
xmantissa/website.py
xmantissa/webtheme.py
xmantissa/benchmarks/benchmark_fulltext.py
xmantissa/benchmarks/benchmark_stats.py
xmantissa/benchmarks/benchmark_stats2.py
xmantissa/js/Fadomatic.js
xmantissa/js/Mantissa/Admin.js
xmantissa/js/Mantissa/Authentication.js
xmantissa/js/Mantissa/AutoComplete.js
xmantissa/js/Mantissa/DOMReplace.js
xmantissa/js/Mantissa/LiveForm.js
xmantissa/js/Mantissa/Offering.js
xmantissa/js/Mantissa/People.js
xmantissa/js/Mantissa/Preferences.js
xmantissa/js/Mantissa/ScrollTable.js
xmantissa/js/Mantissa/StatGraph.js
xmantissa/js/Mantissa/TDB.js
xmantissa/js/Mantissa/Validate.js
xmantissa/js/Mantissa/__init__.js
xmantissa/js/Mantissa/Test/Dummy.js
xmantissa/js/Mantissa/Test/TestAutoComplete.js
xmantissa/js/Mantissa/Test/TestDOMReplace.js
xmantissa/js/Mantissa/Test/TestLiveForm.js
xmantissa/js/Mantissa/Test/TestOffering.js
