Metadata-Version: 2.0
Name: Mantissa
Version: 0.9.0
Summary: A multiprotocol application deployment platform
Home-page: https://github.com/twisted/mantissa
Author: Tristan Seligmann
Author-email: mithrandi@mithrandi.net
License: MIT
Platform: any
Classifier: Development Status :: 5 - Production/Stable
Classifier: Environment :: No Input/Output (Daemon)
Classifier: Framework :: Twisted
Classifier: Intended Audience :: Developers
Classifier: License :: OSI Approved :: MIT License
Classifier: Programming Language :: JavaScript
Classifier: Programming Language :: Python
Classifier: Topic :: Internet
Classifier: Topic :: Internet :: WWW/HTTP :: Dynamic Content
Classifier: Topic :: Software Development :: Libraries :: Application Frameworks
Classifier: Topic :: Terminals
Requires-Dist: Axiom (>=0.7.0)
Requires-Dist: Nevow (>=0.9.5)
Requires-Dist: Pillow
Requires-Dist: PyOpenSSL (>=0.13)
Requires-Dist: PyTZ
Requires-Dist: Twisted[conch,tls] (>=16.6.0)
Requires-Dist: Vertex (>=0.2.0)
Requires-Dist: cryptography (>=1.0)
Requires-Dist: cssutils (>=0.9.5)
